mglg/__init__.py
mglg/ext/__init__.py
mglg/ext/earcut.cpython-37m-darwin.so
mglg/ext/sdf.cpython-37m-darwin.so
mglg/ext/_earcut/__init__.py
mglg/ext/_earcut/earcut.py
mglg/graphics/__init__.py
mglg/graphics/_particle.cpython-37m-darwin.so
mglg/graphics/drawable.py
mglg/graphics/easing.cpython-37m-darwin.so
mglg/graphics/framebuffer.py
mglg/graphics/image.py
mglg/graphics/object.py
mglg/graphics/outline.py
mglg/graphics/particles.py
mglg/graphics/shapes.py
mglg/graphics/stipples.py
mglg/graphics/text.py
mglg/graphics/win.py
mglg/graphics/font/__init__.py
mglg/graphics/font/atlas.py
mglg/graphics/font/font_manager.py
mglg/graphics/font/glyph.py
mglg/graphics/font/sdf_font.py
mglg/graphics/pyimgui/__init__.py
mglg/graphics/pyimgui/glfw_integration.py
mglg/graphics/pyimgui/mgl_integration.py
mglg/util/__init__.py
mglg/util/bench.py
mglg/util/prebake_font.py
mglg/util/profiler.py
mglg-0.2.23.dist-info/LICENSE.txt
mglg-0.2.23.dist-info/METADATA
mglg-0.2.23.dist-info/WHEEL
mglg-0.2.23.dist-info/top_level.txt
mglg-0.2.23.dist-info/RECORD
