Metadata-Version: 2.1
Name: mglg
Version: 0.2.23
Summary: UNKNOWN
Home-page: https://github.com/aforren1/mglg
Author: Alex Forrence
Author-email: alex.forrence@gmail.com
License: UNKNOWN
Platform: UNKNOWN
Classifier: Programming Language :: Python :: 3
Classifier: License :: OSI Approved :: MIT License
Classifier: Operating System :: OS Independent
Requires-Dist: numpy (>=1.19.4)
Requires-Dist: moderngl (==5.6.2)
Requires-Dist: pyglm (>=1.99.3)
Requires-Dist: glfw (>=2.0.0)
Requires-Dist: imgui (>=1.3.0)
Requires-Dist: stbpy (==0.0.5)
Provides-Extra: freetype
Requires-Dist: freetype-py ; extra == 'freetype'
